[
    {
        "name": "Abbaye de la Bussière, Hôtel de luxe et Restaurant gastronomique étoilé dans un parc 1 étoile La Bussière-sur-Ouche – Relais & Châteaux",
        "day": [
            2,
            9,
            16,
            23,
            30
        ],
        "prices": [
            "UNAVAILABLE",
            "UNAVAILABLE",
            "UNAVAILABLE",
            "UNAVAILABLE",
            "UNAVAILABLE"
        ]
    },
    {
        "name": "Auberge des Glazicks, restaurant gastronomique 2 étoiles Michelin et hôtel dans un village à Plomodiern – Relais & Châteaux",
        "day": [
            2,
            9,
            16,
            23,
            30
        ],
        "prices": [
            "UNAVAILABLE",
            "UNAVAILABLE",
            "UNAVAILABLE",
            "UNAVAILABLE",
            "UNAVAILABLE"
        ]
    },
    {
        "name": "Grand Hôtel de Cala Rossa & Spa, Hôtel de luxe et Restaurant gastronomique étoilé en bord de mer 1 étoile Porto-Vecchio – Relais & Châteaux",
        "day": [
            2,
            9,
            16,
            23,
            30
        ],
        "prices": [
            "UNAVAILABLE",
            "UNAVAILABLE",
            "UNAVAILABLE",
            "UNAVAILABLE",
            "UNAVAILABLE"
        ]
    },
    {
        "name": "Hameau Albert Ier, Hôtel de luxe et Restaurant gastronomique étoilé à la montagne 2 étoiles Chamonix-Mont-Blanc – Relais & Châteaux",
        "day": [
            2,
            9,
            16,
            23,
            30
        ],
        "prices": [
            "US$356",
            "US$814",
            "US$627",
            "US$627",
            "US$588"
        ]
    },
    {
        "name": "Hostellerie La Briqueterie, Hôtel de luxe et Restaurant gastronomique étoilé dans un vignoble 1 étoile Vinay – Relais & Châteaux",
        "day": [
            2,
            9,
            16,
            23,
            30
        ],
        "prices": [
            "UNAVAILABLE",
            "US$289",
            "US$311",
            "US$396",
            "US$305"
        ]
    },
    {
        "name": "Hôtel Le Chabichou Restaurants & Spa, Hôtel de luxe et Restaurant gastronomique étoilé à la montagne 2 étoiles Courchevel 1850 – Relais & Châteaux",
        "day": [
            2,
            9,
            16,
            23,
            30
        ],
        "prices": [
            "US$1175",
            "US$735",
            "US$836",
            "US$531",
            "US$735"
        ]
    },
    {
        "name": "Le Clos des Sens, restaurant gastronomique et hôtel à la montagne 2 étoiles à Annecy le Vieux – Relais & Châteaux",
        "day": [
            2,
            9,
            16,
            23,
            30
        ],
        "prices": [
            "UNAVAILABLE",
            "UNAVAILABLE",
            "UNAVAILABLE",
            "UNAVAILABLE",
            "UNAVAILABLE"
        ]
    },
    {
        "name": "Hôtel et Restaurant Régis et Jacques Marcon, Hôtel de luxe et Restaurant gastronomique étoilé dans un village 3 étoiles Saint-Bonnet-le-Froid – Relais & Châteaux",
        "day": [
            2,
            9,
            16,
            23,
            30
        ],
        "prices": [
            "US$452",
            "US$396",
            "US$526",
            "US$757",
            "US$452"
        ]
    },
    {
        "name": "Les Prés d’Eugénie - Michel Guérard, Hôtel de luxe et Restaurant gastronomique étoilé à la campagne 3 étoiles Eugénie-les-Bains – Relais & Châteaux",
        "day": [
            2,
            9,
            16,
            23,
            30
        ],
        "prices": [
            "UNAVAILABLE",
            "UNAVAILABLE",
            "US$209",
            "UNAVAILABLE",
            "US$173"
        ]
    },
    {
        "name": "Maison Decoret, Hôtel de luxe et Restaurant gastronomique étoilé en ville 1 étoile Vichy – Relais & Châteaux",
        "day": [
            2,
            9,
            16,
            23,
            30
        ],
        "prices": [
            "US$186",
            "US$186",
            "US$186",
            "US$168",
            "US$168"
        ]
    },
    {
        "name": "Hotel de la Poste, restaurant gastronomique et hôtel dans un village 1 étoile à Charolles – Relais & Châteaux",
        "day": [
            2,
            9,
            16,
            23,
            30
        ],
        "prices": [
            "US$249",
            "US$204",
            "US$224",
            "US$224",
            "US$224"
        ]
    },
    {
        "name": "Relais de la Poste, Hôtel de luxe et Restaurant gastronomique étoilé dans un village 2 étoiles Magescq – Relais & Châteaux",
        "day": [
            2,
            9,
            16,
            23,
            30
        ],
        "prices": [
            "UNAVAILABLE",
            "UNAVAILABLE",
            "UNAVAILABLE",
            "UNAVAILABLE",
            "UNAVAILABLE"
        ]
    }
]